Metadata-Version: 1.0
Name: short-pygame
Version: 0.0.4
Summary: this is a plugin for shorten your pygame project this is beta test only commands start() and end() for import import short_pygame
Home-page: UNKNOWN
Author: Ivanchik burinki#4376 in discord
Author-email: UNKNOWN
License: UNKNOWN
Platform: UNKNOWN
